webexevents/__init__.py
webexevents/client.py
webexevents/configuration.py
webexevents/constants.py
webexevents/exceptions.py
webexevents/helpers.py
webexevents/http_client.py
webexevents/rate_limiter.py
webexevents/request.py
webexevents/response.py
webex_events-1.0.0.dist-info/LICENSE.txt
webex_events-1.0.0.dist-info/METADATA
webex_events-1.0.0.dist-info/WHEEL
webex_events-1.0.0.dist-info/top_level.txt
webex_events-1.0.0.dist-info/RECORD
