Metadata-Version: 2.1
Name: webex-events
Version: 1.0.0
Summary: Webex Events SDK
Author-email: Webex Events <socio-backend.gen@cisco.com>
Project-URL: Homepage, https://github.com/socioevents/webex-events-python-sdk
Keywords: feed,reader,tutorial
Classifier: License :: OSI Approved :: MIT License
Classifier: Programming Language :: Python
Classifier: Programming Language :: Python :: 3
Requires-Python: >=3.9
License-File: LICENSE.txt
Requires-Dist: requests>=2.32.3
Provides-Extra: dev
Requires-Dist: pip-tools; extra == "dev"
Requires-Dist: pytest; extra == "dev"
